framesss/__init__.py
framesss/__main__.py
framesss/enums.py
framesss/errors.py
framesss/fea/__init__.py
framesss/fea/analysis/__init__.py
framesss/fea/analysis/analysis.py
framesss/fea/analysis/frame_xyz_analysis.py
framesss/fea/analysis/frame_xz_analysis.py
framesss/fea/analysis/grid_xy_analysis.py
framesss/fea/analysis/truss_xyz_analysis.py
framesss/fea/analysis/truss_xz_analysis.py
framesss/fea/boundary_conditions/__init__.py
framesss/fea/boundary_conditions/element_load.py
framesss/fea/boundary_conditions/nodal_load.py
framesss/fea/boundary_conditions/prescribed_displacement.py
framesss/fea/element_1d.py
framesss/fea/models/__init__.py
framesss/fea/models/frame_xz.py
framesss/fea/models/model.py
framesss/fea/node.py
framesss/post/__init__.py
framesss/post/member_1d_results.py
framesss/post/node_results.py
framesss/pre/__init__.py
framesss/pre/cases.py
framesss/pre/material.py
framesss/pre/member_1d.py
framesss/pre/member_load.py
framesss/pre/section.py
framesss/py.typed
framesss/solvers/__init__.py
framesss/solvers/linear_static.py
framesss/solvers/pushover.py
framesss/solvers/solver.py
framesss/utils.py
framesss-0.0.17.dist-info/LICENSE
framesss-0.0.17.dist-info/LICENSE.LESM
framesss-0.0.17.dist-info/METADATA
framesss-0.0.17.dist-info/WHEEL
framesss-0.0.17.dist-info/entry_points.txt
framesss-0.0.17.dist-info/RECORD
