Metadata-Version: 2.1
Name: framesss
Version: 0.0.17
Summary: framesss
Home-page: https://github.com/DanBeranek/framesss
License: MIT
Author: Daniel Beranek
Author-email: daniel.beraanek@gmail.com
Requires-Python: >=3.9,<4.0
Classifier: Development Status :: 2 - Pre-Alpha
Classifier: License :: OSI Approved :: MIT License
Classifier: Programming Language :: Python :: 3
Classifier: Programming Language :: Python :: 3.9
Classifier: Programming Language :: Python :: 3.10
Classifier: Programming Language :: Python :: 3.11
Classifier: Programming Language :: Python :: 3.12
Requires-Dist: aenum (>=3.1.15,<4.0.0)
Requires-Dist: click (>=8.0.1)
Requires-Dist: numpy (>=1.26.4,<2.0.0)
Requires-Dist: scipy (>=1.12.0,<2.0.0)
Project-URL: Changelog, https://github.com/DanBeranek/framesss/releases
Project-URL: Documentation, https://DanBeranek.github.io/framesss
Project-URL: Repository, https://github.com/DanBeranek/framesss
